<polygon volume="inside">
 <node lon="5.68644569343405" lat="60.4357554342701"/>
 <node lon="5.69083317503344" lat="60.4360625890296"/>
 <node lon="5.69103405180395" lat="60.4360764722117"/>
 <node lon="5.69406487424014" lat="60.4362856556544"/>
 <node lon="5.69414130229999" lat="60.4362908583113"/>
 <node lon="5.69592917187297" lat="60.4364098187413"/>
 <node lon="5.69919695185748" lat="60.4367471264514"/>
 <node lon="5.69942601844764" lat="60.4367704844776"/>
 <node lon="5.703708601679" lat="60.4372048754388"/>
 <node lon="5.70667769664546" lat="60.4375037062553"/>
 <node lon="5.70668427976869" lat="60.4375043501155"/>
 <node lon="5.71548581926279" lat="60.4383864847892"/>
 <node lon="5.71604545386801" lat="60.4384480481782"/>
 <node lon="5.71617676832842" lat="60.4384818642997"/>
 <node lon="5.71782512573825" lat="60.4389044074704"/>
 <node lon="5.71963381489153" lat="60.4390711443642"/>
 <node lon="5.7228285419436" lat="60.4394393219055"/>
 <node lon="5.72828608367052" lat="60.4400464040136"/>
 <node lon="5.72995744085235" lat="60.4402361720001"/>
 <node lon="5.73174062338512" lat="60.4404360215535"/>
 <node lon="5.73232812825945" lat="60.4405707925881"/>
 <node lon="5.73290702791445" lat="60.4407036916688"/>
 <node lon="5.73292783633488" lat="60.4407083150007"/>
 <node lon="5.73294313518493" lat="60.4407117383342"/>
 <node lon="5.73489265374705" lat="60.441149206254"/>
 <node lon="5.74194801432496" lat="60.442732106876"/>
 <node lon="5.74027866585551" lat="60.4456421334238"/>
 <node lon="5.74196708773329" lat="60.4483045074634"/>
 <node lon="5.74197918090259" lat="60.4483165640054"/>
 <node lon="5.74639373496775" lat="60.4493165553037"/>
 <node lon="5.74841595899097" lat="60.4497746098138"/>
 <node lon="5.74856926478899" lat="60.4498092060853"/>
 <node lon="5.74875105349869" lat="60.4498504061678"/>
 <node lon="5.74880104491559" lat="60.4498617700083"/>
 <node lon="5.75747490988289" lat="60.451825831751"/>
 <node lon="5.76571634988658" lat="60.4533367368396"/>
 <node lon="5.76976526350835" lat="60.4543941293748"/>
 <node lon="5.77052925934474" lat="60.45418596454"/>
 <node lon="5.77069639172913" lat="60.4541404144107"/>
 <node lon="5.77580204367304" lat="60.4527487634876"/>
 <node lon="5.77776077959511" lat="60.4522148086098"/>
 <node lon="5.78514119596823" lat="60.4502224938791"/>
 <node lon="5.78708838199095" lat="60.4493498140175"/>
 <node lon="5.79017646723662" lat="60.4500120137229"/>
 <node lon="5.79034215205451" lat="60.4500476024943"/>
 <node lon="5.790406133291" lat="60.4500612804689"/>
 <node lon="5.790519747502" lat="60.4510021310852"/>
 <node lon="5.7909533642556" lat="60.4545957699533"/>
 <node lon="5.79119853023354" lat="60.4566282267506"/>
 <node lon="5.79120029888316" lat="60.4566425414848"/>
 <node lon="5.79141734070292" lat="60.4583114706475"/>
 <node lon="5.7914250369462" lat="60.4583703999148"/>
 <node lon="5.79155725799052" lat="60.459392993523"/>
 <node lon="5.79651933442537" lat="60.461246794603"/>
 <node lon="5.79857113508431" lat="60.4620130372189"/>
 <node lon="5.79857524273823" lat="60.4620146789612"/>
 <node lon="5.79876576601469" lat="60.4620853367895"/>
 <node lon="5.79880465640974" lat="60.4620997941734"/>
 <node lon="5.8000711629769" lat="60.4625693788084"/>
 <node lon="5.80013421107781" lat="60.4625928383853"/>
 <node lon="5.8001724606368" lat="60.4626069795447"/>
 <node lon="5.80036563517412" lat="60.4626786327343"/>
 <node lon="5.80142755335573" lat="60.4630711451686"/>
 <node lon="5.80941380306327" lat="60.4643251423002"/>
 <node lon="5.81900910928765" lat="60.4658248564647"/>
 <node lon="5.82424555490188" lat="60.4666844714767"/>
 <node lon="5.82606025926932" lat="60.4669824819417"/>
 <node lon="5.8262430197822" lat="60.4670125156469"/>
 <node lon="5.82643801952261" lat="60.4670445732084"/>
 <node lon="5.82781690919642" lat="60.467271015757"/>
 <node lon="5.82912553983998" lat="60.4674857912742"/>
 <node lon="5.82920682707904" lat="60.4674992924419"/>
 <node lon="5.82921334358288" lat="60.4675001963124"/>
 <node lon="5.82946413176228" lat="60.4675414509967"/>
 <node lon="5.83005215409388" lat="60.4676379979694"/>
 <node lon="5.83278678345684" lat="60.4673518990679"/>
 <node lon="5.83778333771811" lat="60.4668287662945"/>
 <node lon="5.83885690713225" lat="60.467152520981"/>
 <node lon="5.84305857112143" lat="60.4684191560686"/>
 <node lon="5.84403797686425" lat="60.4687144701305"/>
 <node lon="5.84423948938091" lat="60.4687752414791"/>
 <node lon="5.84548121926727" lat="60.4691493536795"/>
 <node lon="5.8483289422177" lat="60.4700077086398"/>
 <node lon="5.8499392427001" lat="60.4704929637266"/>
 <node lon="5.85010353674644" lat="60.4705423827005"/>
 <node lon="5.85216693839606" lat="60.4711653377745"/>
 <node lon="5.86059416510239" lat="60.4744517837537"/>
 <node lon="5.86075706352872" lat="60.4745152814523"/>
 <node lon="5.86915831908888" lat="60.4777905377801"/>
 <node lon="5.87044668210277" lat="60.4783013694466"/>
 <node lon="5.87208529956844" lat="60.4789411994793"/>
 <node lon="5.87232156778561" lat="60.4790335140796"/>
 <node lon="5.87236064595763" lat="60.4790487736622"/>
 <node lon="5.87258408598523" lat="60.4791359545962"/>
 <node lon="5.87586197099262" lat="60.4804160271105"/>
 <node lon="5.87603200131526" lat="60.4804823449927"/>
 <node lon="5.8771546140055" lat="60.4809208424372"/>
 <node lon="5.87932290061008" lat="60.48176068582"/>
 <node lon="5.87986273751429" lat="60.4832430908296"/>
 <node lon="5.88029956171053" lat="60.4844425490359"/>
 <node lon="5.88074143852377" lat="60.485649492927"/>
 <node lon="5.88134472272833" lat="60.4872970472429"/>
 <node lon="5.88150708645651" lat="60.4877387201171"/>
 <node lon="5.88259650508096" lat="60.4907047974174"/>
 <node lon="5.88260023824411" lat="60.490714906131"/>
 <node lon="5.88265634434847" lat="60.4908674481032"/>
 <node lon="5.88267415007645" lat="60.4909158536374"/>
 <node lon="5.88299310325009" lat="60.4917842439112"/>
 <node lon="5.88411837638345" lat="60.4948542658791"/>
 <node lon="5.88413856255136" lat="60.4949091616635"/>
 <node lon="5.88419629651638" lat="60.4950171667004"/>
 <node lon="5.88388333521748" lat="60.4951350634621"/>
 <node lon="5.88390832677642" lat="60.4951749256855"/>
 <node lon="5.88394272250523" lat="60.4952126339754"/>
 <node lon="5.88397676512762" lat="60.4952593559626"/>
 <node lon="5.88398336187938" lat="60.4952878283285"/>
 <node lon="5.8839646373414" lat="60.4953093142294"/>
 <node lon="5.88393436510532" lat="60.4953308180191"/>
 <node lon="5.88388794081707" lat="60.4953465996682"/>
 <node lon="5.88384373126965" lat="60.495363618445"/>
 <node lon="5.88381366061592" lat="60.4953805267015"/>
 <node lon="5.88378545952734" lat="60.4954089516794"/>
 <node lon="5.8837874880457" lat="60.4954373804886"/>
 <node lon="5.88379183671037" lat="60.4954634384865"/>
 <node lon="5.8837799310548" lat="60.4954919015268"/>
 <node lon="5.88377472558582" lat="60.49550058095"/>
 <node lon="5.88376774312596" lat="60.4955123012661"/>
 <node lon="5.88376556792097" lat="60.4955374579206"/>
 <node lon="5.88369942746463" lat="60.4955762839405"/>
 <node lon="5.88359377940319" lat="60.4956291085083"/>
 <node lon="5.88283585564229" lat="60.4961847897949"/>
 <node lon="5.88273872551544" lat="60.4962702858083"/>
 <node lon="5.88270825364468" lat="60.4962970177195"/>
 <node lon="5.88270687813449" lat="60.4962986401784"/>
 <node lon="5.88255497015951" lat="60.4964591737953"/>
 <node lon="5.88254533526442" lat="60.4966847325234"/>
 <node lon="5.88256121880705" lat="60.4968874659582"/>
 <node lon="5.8825424017095" lat="60.4970367435182"/>
 <node lon="5.882571235447" lat="60.4971892138062"/>
 <node lon="5.88270305232086" lat="60.4972801805651"/>
 <node lon="5.88294958519863" lat="60.4975535754663"/>
 <node lon="5.88294884200942" lat="60.4977037367228"/>
 <node lon="5.88292062920519" lat="60.4978402559911"/>
 <node lon="5.88310465317355" lat="60.4979358131775"/>
 <node lon="5.88312983199512" lat="60.4980131963355"/>
 <node lon="5.88311224434841" lat="60.4980727203764"/>
 <node lon="5.88304596371783" lat="60.4981430795249"/>
 <node lon="5.88302228266434" lat="60.498168471826"/>
 <node lon="5.88301519591267" lat="60.4981760274596"/>
 <node lon="5.88244573103221" lat="60.4990002899762"/>
 <node lon="5.88227807177434" lat="60.4994370266972"/>
 <node lon="5.8823089211818" lat="60.4997260203854"/>
 <node lon="5.88232299349122" lat="60.4998574996126"/>
 <node lon="5.88234384285612" lat="60.50093365271"/>
 <node lon="5.88234576401149" lat="60.5010226292864"/>
 <node lon="5.88234577363982" lat="60.5010323006836"/>
 <node lon="5.88234692299645" lat="60.5010884158972"/>
 <node lon="5.8840829145278" lat="60.5021261804233"/>
 <node lon="5.88630044299825" lat="60.5034513168454"/>
 <node lon="5.88651121980672" lat="60.5035774505342"/>
 <node lon="5.88822273800289" lat="60.5046002678052"/>
 <node lon="5.88838152661737" lat="60.5046951624461"/>
 <node lon="5.88890104819813" lat="60.5050035127675"/>
 <node lon="5.89728600442006" lat="60.5099713257554"/>
 <node lon="5.89948835395123" lat="60.5112850254044"/>
 <node lon="5.90147843039818" lat="60.5127730717872"/>
 <node lon="5.90367604403674" lat="60.5157343148783"/>
 <node lon="5.90926327332018" lat="60.5210989746699"/>
 <node lon="5.90970054282878" lat="60.5214202830745"/>
 <node lon="5.9109087299146" lat="60.5222851704942"/>
 <node lon="5.91334860832138" lat="60.5240920716223"/>
 <node lon="5.91639424607754" lat="60.5265756377547"/>
 <node lon="5.91850931934107" lat="60.5261934507264"/>
 <node lon="5.91866259401449" lat="60.5261656427295"/>
 <node lon="5.91942222126119" lat="60.5260283970629"/>
 <node lon="5.9219727708962" lat="60.5255674781766"/>
 <node lon="5.92261542159311" lat="60.5253891185137"/>
 <node lon="5.92268070837503" lat="60.5253709095907"/>
 <node lon="5.92862405666662" lat="60.523721613323"/>
 <node lon="5.9306331155328" lat="60.5230735132948"/>
 <node lon="5.93083057400617" lat="60.5230098574788"/>
 <node lon="5.93184232057582" lat="60.5226834887846"/>
 <node lon="5.93519665980484" lat="60.5221240146023"/>
 <node lon="5.93921645716144" lat="60.5214589843259"/>
 <node lon="5.94008468685173" lat="60.5213148720256"/>
 <node lon="5.94035833930299" lat="60.5212696112135"/>
 <node lon="5.94045860036969" lat="60.5212527932051"/>
 <node lon="5.94089668817861" lat="60.5211802827279"/>
 <node lon="5.9516890844987" lat="60.5193894154925"/>
 <node lon="5.95184083344865" lat="60.5193641787589"/>
 <node lon="5.95188661188058" lat="60.5193565527491"/>
 <node lon="5.95264584269778" lat="60.5192305803421"/>
 <node lon="5.95278256242281" lat="60.5192079305392"/>
 <node lon="5.95285083227851" lat="60.5191965994381"/>
 <node lon="5.95461411229736" lat="60.5189038886086"/>
 <node lon="5.9549381693286" lat="60.518850023425"/>
 <node lon="5.95583622152751" lat="60.5187009831555"/>
 <node lon="5.95644775777907" lat="60.518599423797"/>
 <node lon="5.96445535545917" lat="60.5172696492823"/>
 <node lon="5.9645991630055" lat="60.5172458450387"/>
 <node lon="5.96555657053281" lat="60.5170867858765"/>
 <node lon="5.96967884805498" lat="60.51310996572"/>
 <node lon="5.96974160111537" lat="60.513049631761"/>
 <node lon="5.97245634284073" lat="60.5104300726643"/>
 <node lon="5.97265960643882" lat="60.5102340057858"/>
 <node lon="5.9728247637653" lat="60.510074470123"/>
 <node lon="5.97291649223848" lat="60.5099859277689"/>
 <node lon="5.97413670876257" lat="60.508808299225"/>
 <node lon="5.97910098385031" lat="60.507159376375"/>
 <node lon="5.97928449134512" lat="60.5070983213896"/>
 <node lon="5.97958496253549" lat="60.5069985158085"/>
 <node lon="5.98166397319524" lat="60.5063078748376"/>
 <node lon="5.9819577506297" lat="60.506210319579"/>
 <node lon="5.98259182523406" lat="60.5059995797236"/>
 <node lon="5.98263950359365" lat="60.505983759898"/>
 <node lon="5.98278722067921" lat="60.5059346311665"/>
 <node lon="5.98281486132589" lat="60.5059255794691"/>
 <node lon="5.98322627617494" lat="60.5057887724836"/>
 <node lon="5.98688407921702" lat="60.5045648827984"/>
 <node lon="5.9894323609264" lat="60.5037073688505"/>
 <node lon="5.98964967393085" lat="60.5036340533886"/>
 <node lon="5.99107052445098" lat="60.5031558472952"/>
 <node lon="5.98950320484533" lat="60.501419952032"/>
 <node lon="5.98939384587388" lat="60.5012987362628"/>
 <node lon="5.98817752963782" lat="60.4999524256114"/>
 <node lon="5.98739110986597" lat="60.499072205454"/>
 <node lon="5.9873744264572" lat="60.4958286193171"/>
 <node lon="5.99085121870945" lat="60.4937820418713"/>
 <node lon="5.99070343182878" lat="60.4929737765377"/>
 <node lon="5.99041324522647" lat="60.4913871612793"/>
 <node lon="5.99006818091149" lat="60.4910891365253"/>
 <node lon="5.99001580733468" lat="60.4910439119714"/>
 <node lon="5.98989041128463" lat="60.4909356102712"/>
 <node lon="5.98985247779693" lat="60.4909029356473"/>
 <node lon="5.98916972522134" lat="60.490313347533"/>
 <node lon="5.98820355839674" lat="60.489261207464"/>
 <node lon="5.98483595824764" lat="60.4862876625497"/>
 <node lon="5.98445386537849" lat="60.4839782393848"/>
 <node lon="5.98206686850625" lat="60.4784090937685"/>
 <node lon="5.98197884446308" lat="60.4782034729818"/>
 <node lon="5.98158213329723" lat="60.477275471247"/>
 <node lon="5.98100245884591" lat="60.4759192150989"/>
 <node lon="5.98055707506815" lat="60.4748774611403"/>
 <node lon="5.97934302135872" lat="60.4720366722309"/>
 <node lon="5.97928019680462" lat="60.4718896077459"/>
 <node lon="5.97896259772811" lat="60.4711464566149"/>
 <node lon="5.97390446285047" lat="60.465363432606"/>
 <node lon="5.96961302615507" lat="60.4631497203359"/>
 <node lon="5.96573696470616" lat="60.4611497448818"/>
 <node lon="5.96551057403047" lat="60.4610328856536"/>
 <node lon="5.95967508406116" lat="60.4580213431914"/>
 <node lon="5.9575132527499" lat="60.457777473195"/>
 <node lon="5.95713196189657" lat="60.4576604879246"/>
 <node lon="5.95672930285857" lat="60.457350184645"/>
 <node lon="5.95673354047136" lat="60.4570687911869"/>
 <node lon="5.9567340158641" lat="60.4570409897421"/>
 <node lon="5.95667423434523" lat="60.4569461699954"/>
 <node lon="5.95661528176418" lat="60.4568523105964"/>
 <node lon="5.9561825031822" lat="60.4561247851895"/>
 <node lon="5.95615222182638" lat="60.4560735528725"/>
 <node lon="5.95233940042348" lat="60.4496590404824"/>
 <node lon="5.94912353908414" lat="60.4442467725384"/>
 <node lon="5.94786114678378" lat="60.4421214811933"/>
 <node lon="5.94777435850437" lat="60.4419751019015"/>
 <node lon="5.94754155498852" lat="60.4415831266945"/>
 <node lon="5.94744388285375" lat="60.4414188312725"/>
 <node lon="5.94708326797907" lat="60.4408116046222"/>
 <node lon="5.9452406275928" lat="60.4374132416316"/>
 <node lon="5.94521993941639" lat="60.4373748626413"/>
 <node lon="5.94440300914821" lat="60.4358678975869"/>
 <node lon="5.94432024447587" lat="60.435715102898"/>
 <node lon="5.94400760325616" lat="60.435136724755"/>
 <node lon="5.94214740702471" lat="60.431671389471"/>
 <node lon="5.93844793087271" lat="60.4292762495755"/>
 <node lon="5.93649460243953" lat="60.4280113842709"/>
 <node lon="5.9364050449963" lat="60.4279389992967"/>
 <node lon="5.93551839234147" lat="60.4272231677205"/>
 <node lon="5.93459755276583" lat="60.4264710032201"/>
 <node lon="5.93347465967263" lat="60.4255537744929"/>
 <node lon="5.93026735904653" lat="60.4229336483445"/>
 <node lon="5.92992627994144" lat="60.4226680373098"/>
 <node lon="5.92921878644893" lat="60.4221170884131"/>
 <node lon="5.92828727959967" lat="60.4213915176291"/>
 <node lon="5.92406461041154" lat="60.4181024880081"/>
 <node lon="5.92405246879339" lat="60.4180819525302"/>
 <node lon="5.92290846896124" lat="60.4161269338813"/>
 <node lon="5.92151232343317" lat="60.4137410223725"/>
 <node lon="5.92079553576366" lat="60.4125167224002"/>
 <node lon="5.91898477298746" lat="60.4094212153515"/>
 <node lon="5.91738269761215" lat="60.4066810008509"/>
 <node lon="5.91747179845435" lat="60.4066695046078"/>
 <node lon="5.91759822743069" lat="60.4066532547022"/>
 <node lon="5.91757136514017" lat="60.4052931753595"/>
 <node lon="5.91681751728826" lat="60.4045652475478"/>
 <node lon="5.91693233668095" lat="60.4041144043764"/>
 <node lon="5.91739696534568" lat="60.4037039744979"/>
 <node lon="5.91740719645479" lat="60.4035524881176"/>
 <node lon="5.91738315275767" lat="60.4033929512226"/>
 <node lon="5.91721965364996" lat="60.4032141542809"/>
 <node lon="5.91724807072834" lat="60.4030649126305"/>
 <node lon="5.91711768199234" lat="60.4029191195967"/>
 <node lon="5.91690272318403" lat="60.4027498874719"/>
 <node lon="5.91683539713114" lat="60.4025448075502"/>
 <node lon="5.91693580971785" lat="60.4024006979558"/>
 <node lon="5.91683550376569" lat="60.4021524104612"/>
 <node lon="5.91683277532915" lat="60.4016667331011"/>
 <node lon="5.91692770666546" lat="60.4015525220241"/>
 <node lon="5.91700031935991" lat="60.4014007167519"/>
 <node lon="5.91707217967712" lat="60.4013751123051"/>
 <node lon="5.91705135593883" lat="60.4012080245474"/>
 <node lon="5.91711072712542" lat="60.401091639008"/>
 <node lon="5.91720342881431" lat="60.4008767786007"/>
 <node lon="5.91753818417354" lat="60.4006885054308"/>
 <node lon="5.91755036027579" lat="60.4006211104098"/>
 <node lon="5.91745371981844" lat="60.4004976108927"/>
 <node lon="5.91746849574252" lat="60.4004021076071"/>
 <node lon="5.9177039061439" lat="60.4003229520922"/>
 <node lon="5.91789000319193" lat="60.400222962908"/>
 <node lon="5.91802745304975" lat="60.400155687429"/>
 <node lon="5.918012418507" lat="60.4001370306439"/>
 <node lon="5.91799563062387" lat="60.4000264333827"/>
 <node lon="5.9179962497278" lat="60.3996997742522"/>
 <node lon="5.91789182093432" lat="60.3996183055675"/>
 <node lon="5.91781534587631" lat="60.3995719263587"/>
 <node lon="5.91780456462543" lat="60.3995205755417"/>
 <node lon="5.9178414088403" lat="60.3994570459323"/>
 <node lon="5.91784062638306" lat="60.3993414942457"/>
 <node lon="5.91765519108463" lat="60.399092594804"/>
 <node lon="5.91723518644995" lat="60.398893897362"/>
 <node lon="5.91604817804582" lat="60.398671905237"/>
 <node lon="5.91579334185943" lat="60.3985335461357"/>
 <node lon="5.91555030910384" lat="60.3982712819727"/>
 <node lon="5.91558861617001" lat="60.3979282357378"/>
 <node lon="5.91712656113345" lat="60.3969094052963"/>
 <node lon="5.91741464179934" lat="60.3965750431331"/>
 <node lon="5.91780612094161" lat="60.3961632018357"/>
 <node lon="5.91783813843618" lat="60.3957943287372"/>
 <node lon="5.91749792670606" lat="60.3957974101048"/>
 <node lon="5.91708568118241" lat="60.3956778692598"/>
 <node lon="5.91679779569328" lat="60.3954673790647"/>
 <node lon="5.9168219371824" lat="60.3952618120429"/>
 <node lon="5.91683561420123" lat="60.395153309902"/>
 <node lon="5.91711143258196" lat="60.3947929817376"/>
 <node lon="5.91720892471926" lat="60.39441794791"/>
 <node lon="5.91707838480852" lat="60.3847894886651"/>
 <node lon="5.91707771513204" lat="60.3847788688679"/>
 <node lon="5.91707770056757" lat="60.3847769700176"/>
 <node lon="5.91607128812301" lat="60.3824956487792"/>
 <node lon="5.91573965293965" lat="60.3810149187754"/>
 <node lon="5.91524737030358" lat="60.3787482663407"/>
 <node lon="5.91521594975617" lat="60.3785578552956"/>
 <node lon="5.91632711669031" lat="60.3755530295617"/>
 <node lon="5.91692199784403" lat="60.3739441053326"/>
 <node lon="5.91708466548799" lat="60.373504335013"/>
 <node lon="5.91911545650395" lat="60.3720500586003"/>
 <node lon="5.91997215480682" lat="60.3706585072444"/>
 <node lon="5.91998717232407" lat="60.3706140827051"/>
 <node lon="5.91952211856295" lat="60.3692872232481"/>
 <node lon="5.92132479106268" lat="60.3664411298484"/>
 <node lon="5.9214280020389" lat="60.3662780576687"/>
 <node lon="5.931283684855" lat="60.3507074141473"/>
 <node lon="5.93141205995038" lat="60.3505042272273"/>
 <node lon="5.93154333963458" lat="60.3502971732089"/>
 <node lon="5.93228175428048" lat="60.3491297236367"/>
 <node lon="5.93278272783858" lat="60.3483204513212"/>
 <node lon="5.93170337886199" lat="60.3456071607545"/>
 <node lon="5.93168005978674" lat="60.3455484433332"/>
 <node lon="5.92831100435571" lat="60.3370750332431"/>
 <node lon="5.92714645142235" lat="60.3341448896883"/>
 <node lon="5.9270037135003" lat="60.3337860562321"/>
 <node lon="5.91741517061358" lat="60.3294848766296"/>
 <node lon="5.91315054229606" lat="60.3275741348413"/>
 <node lon="5.90848715433421" lat="60.3254330311553"/>
 <node lon="5.89894156383131" lat="60.3250631918599"/>
 <node lon="5.88922181336767" lat="60.3247239050663"/>
 <node lon="5.87117544298172" lat="60.3254584118954"/>
 <node lon="5.84342487549447" lat="60.3261981109904"/>
 <node lon="5.83476467150084" lat="60.3289979634692"/>
 <node lon="5.81284318483219" lat="60.3252961688332"/>
 <node lon="5.79427640806766" lat="60.3248821012208"/>
 <node lon="5.78566458518115" lat="60.3290990494266"/>
 <node lon="5.78047444457199" lat="60.3285013735932"/>
 <node lon="5.77317340115365" lat="60.3242068120362"/>
 <node lon="5.77038760956795" lat="60.322587943966"/>
 <node lon="5.76844209086904" lat="60.3232114556414"/>
 <node lon="5.7644512863634" lat="60.3244904634947"/>
 <node lon="5.76412135270252" lat="60.3245960671646"/>
 <node lon="5.76365798109363" lat="60.331992265104"/>
 <node lon="5.76297964947572" lat="60.332939969823"/>
 <node lon="5.76402928891413" lat="60.336028015416"/>
 <node lon="5.76168979468057" lat="60.3368934293145"/>
 <node lon="5.76464109632361" lat="60.3402201746333"/>
 <node lon="5.76464363256558" lat="60.34022279287"/>
 <node lon="5.76431219551654" lat="60.3439653541949"/>
 <node lon="5.76053347936256" lat="60.3455178479052"/>
 <node lon="5.75195859519262" lat="60.3490017499128"/>
 <node lon="5.7495320177215" lat="60.3500396151823"/>
 <node lon="5.74712805764392" lat="60.3510411543235"/>
 <node lon="5.74598990261099" lat="60.3510959014154"/>
 <node lon="5.74515416093639" lat="60.351134887599"/>
 <node lon="5.74464114652913" lat="60.3510864137879"/>
 <node lon="5.74343058618334" lat="60.3509578874397"/>
 <node lon="5.74290601407287" lat="60.3509128440522"/>
 <node lon="5.74200374721448" lat="60.3508290834364"/>
 <node lon="5.74081238250141" lat="60.3508497678976"/>
 <node lon="5.74073454049408" lat="60.3511328483188"/>
 <node lon="5.74060698301214" lat="60.3517014358598"/>
 <node lon="5.74023815119966" lat="60.352353244147"/>
 <node lon="5.74005258096722" lat="60.3527297344091"/>
 <node lon="5.73955243729644" lat="60.3536160322986"/>
 <node lon="5.73956669950543" lat="60.352476590362"/>
 <node lon="5.73958063647919" lat="60.3515545296397"/>
 <node lon="5.73960047327831" lat="60.3511247309271"/>
 <node lon="5.7396014857259" lat="60.350584682749"/>
 <node lon="5.73958898096469" lat="60.3500765898716"/>
 <node lon="5.7395886266747" lat="60.3489965075802"/>
 <node lon="5.73957969520292" lat="60.3485435364257"/>
 <node lon="5.73746208283285" lat="60.3481795925213"/>
 <node lon="5.73746121404298" lat="60.3481794411063"/>
 <node lon="5.73720298315362" lat="60.3472741503524"/>
 <node lon="5.73644567117209" lat="60.3463612827191"/>
 <node lon="5.73591505346514" lat="60.3458950755009"/>
 <node lon="5.73577024035222" lat="60.3457681096313"/>
 <node lon="5.73548875375843" lat="60.3455208056892"/>
 <node lon="5.7350730519816" lat="60.34541304585"/>
 <node lon="5.73503223500465" lat="60.3442191976048"/>
 <node lon="5.73475236087337" lat="60.3438585562814"/>
 <node lon="5.73441806689107" lat="60.3434968926646"/>
 <node lon="5.73405131862248" lat="60.3425492533413"/>
 <node lon="5.73404990684577" lat="60.3425458998431"/>
 <node lon="5.73390066728016" lat="60.3421539371812"/>
 <node lon="5.73367928842986" lat="60.3418464884038"/>
 <node lon="5.73344456639541" lat="60.3415793224937"/>
 <node lon="5.73263470702333" lat="60.3405015515949"/>
 <node lon="5.73294248437936" lat="60.3379700952297"/>
 <node lon="5.73302748669833" lat="60.3368498117746"/>
 <node lon="5.73223098334257" lat="60.3364098202561"/>
 <node lon="5.73157710927877" lat="60.3337430597034"/>
 <node lon="5.73092307405696" lat="60.3328907353167"/>
 <node lon="5.73012638548027" lat="60.3322382785197"/>
 <node lon="5.72940388679211" lat="60.3316465365577"/>
 <node lon="5.7273824909328" lat="60.3297683783023"/>
 <node lon="5.72671917097418" lat="60.3291402812439"/>
 <node lon="5.7261770137443" lat="60.3284392550273"/>
 <node lon="5.72568454867844" lat="60.3278022882202"/>
 <node lon="5.72493917837781" lat="60.327239459071"/>
 <node lon="5.72381948035355" lat="60.3264469781539"/>
 <node lon="5.72342365597458" lat="60.3262395019864"/>
 <node lon="5.72295610363832" lat="60.3260832944376"/>
 <node lon="5.72255777085664" lat="60.3259502172325"/>
 <node lon="5.72245209106359" lat="60.3259048120508"/>
 <node lon="5.72239556030784" lat="60.3258806744736"/>
 <node lon="5.72223471082828" lat="60.325871342154"/>
 <node lon="5.7219805392329" lat="60.326085504912"/>
 <node lon="5.72164143924341" lat="60.3261849401961"/>
 <node lon="5.72107881431143" lat="60.3261277997059"/>
 <node lon="5.72079845317265" lat="60.3262894939496"/>
 <node lon="5.72062979160216" lat="60.3263666635993"/>
 <node lon="5.72028589218541" lat="60.3264841087843"/>
 <node lon="5.72006263131689" lat="60.3263438222164"/>
 <node lon="5.71995247884815" lat="60.3261478575274"/>
 <node lon="5.71965919367225" lat="60.3258828620756"/>
 <node lon="5.7192942338646" lat="60.3255848861977"/>
 <node lon="5.71906956680901" lat="60.3254520919556"/>
 <node lon="5.71891986924259" lat="60.3252465617643"/>
 <node lon="5.71887481694439" lat="60.3251416006293"/>
 <node lon="5.7181174623086" lat="60.3250070039424"/>
 <node lon="5.7177327022721" lat="60.3253047130366"/>
 <node lon="5.71753998499783" lat="60.325467148585"/>
 <node lon="5.7174845872642" lat="60.3254919038968"/>
 <node lon="5.71745913259373" lat="60.3255031287997"/>
 <node lon="5.71740230617466" lat="60.3254978614217"/>
 <node lon="5.71730514176793" lat="60.3254564865125"/>
 <node lon="5.7170962607151" lat="60.3254786592282"/>
 <node lon="5.71691582937407" lat="60.3254333183686"/>
 <node lon="5.71683966565836" lat="60.3254032755518"/>
 <node lon="5.71660844743504" lat="60.3253614990244"/>
 <node lon="5.71642726236945" lat="60.3254002658857"/>
 <node lon="5.71591693430562" lat="60.3253890922154"/>
 <node lon="5.71574436334418" lat="60.3251686577006"/>
 <node lon="5.71552253890397" lat="60.32506227255"/>
 <node lon="5.71533423495928" lat="60.3249120540922"/>
 <node lon="5.7147969827412" lat="60.3247218869928"/>
 <node lon="5.71463730356583" lat="60.324704672288"/>
 <node lon="5.71424791445492" lat="60.3245608975746"/>
 <node lon="5.71363698648247" lat="60.3244351424144"/>
 <node lon="5.71298076189407" lat="60.3242117252214"/>
 <node lon="5.71260384603004" lat="60.3241542514327"/>
 <node lon="5.71251637116561" lat="60.3241668909837"/>
 <node lon="5.71237173667363" lat="60.3241544397863"/>
 <node lon="5.71213090576796" lat="60.324024741713"/>
 <node lon="5.71187274809018" lat="60.3239637914833"/>
 <node lon="5.71166048637434" lat="60.323922708457"/>
 <node lon="5.71135833145008" lat="60.3236584213399"/>
 <node lon="5.71092603469258" lat="60.3235970395329"/>
 <node lon="5.71070987952842" lat="60.3236306218472"/>
 <node lon="5.71031099564396" lat="60.3236053118895"/>
 <node lon="5.71005564287179" lat="60.3233972036404"/>
 <node lon="5.70982009316904" lat="60.3231499009783"/>
 <node lon="5.70970180109937" lat="60.3231002505123"/>
 <node lon="5.70914756476169" lat="60.3230000738203"/>
 <node lon="5.70873110465443" lat="60.3230284829351"/>
 <node lon="5.70839133788239" lat="60.3232745567031"/>
 <node lon="5.70793457728478" lat="60.3233424298074"/>
 <node lon="5.7072810292938" lat="60.3232383174598"/>
 <node lon="5.70693908128505" lat="60.3232407863207"/>
 <node lon="5.70683971248125" lat="60.3231772800238"/>
 <node lon="5.70666918729879" lat="60.3230758508433"/>
 <node lon="5.70636761126146" lat="60.3230926455242"/>
 <node lon="5.7062112808034" lat="60.3231267323186"/>
 <node lon="5.70594256945876" lat="60.3231185424606"/>
 <node lon="5.70573902064917" lat="60.3228233151417"/>
 <node lon="5.70554218943456" lat="60.3226845922738"/>
 <node lon="5.70520686408456" lat="60.32253556009"/>
 <node lon="5.70487086572452" lat="60.3224359285495"/>
 <node lon="5.70447527577079" lat="60.3223559590691"/>
 <node lon="5.70427105319318" lat="60.3223383918851"/>
 <node lon="5.7040882412113" lat="60.3223389681647"/>
 <node lon="5.70391663738386" lat="60.3224434818875"/>
 <node lon="5.70357087573977" lat="60.3226130947685"/>
 <node lon="5.70328126210642" lat="60.3226212338851"/>
 <node lon="5.70279855719175" lat="60.3226568845188"/>
 <node lon="5.70270061524263" lat="60.3227702089419"/>
 <node lon="5.70257833924648" lat="60.3228539733403"/>
 <node lon="5.70219491078784" lat="60.3228046871308"/>
 <node lon="5.70177764786404" lat="60.3227608777416"/>
 <node lon="5.70165107267371" lat="60.3227515866734"/>
 <node lon="5.70154205927054" lat="60.3227871981198"/>
 <node lon="5.70138297654819" lat="60.323128267896"/>
 <node lon="5.70132016527996" lat="60.3232353915223"/>
 <node lon="5.70120881581915" lat="60.323477404431"/>
 <node lon="5.70127780723474" lat="60.3237827648725"/>
 <node lon="5.70136121108318" lat="60.3244471302352"/>
 <node lon="5.70128585160136" lat="60.3247161811277"/>
 <node lon="5.70108433496158" lat="60.3249490308016"/>
 <node lon="5.70075723929215" lat="60.3250737602248"/>
 <node lon="5.69997836020768" lat="60.3251255712811"/>
 <node lon="5.69889254990777" lat="60.3251047332069"/>
 <node lon="5.69806082539131" lat="60.3250306715463"/>
 <node lon="5.69746443478453" lat="60.3249573029617"/>
 <node lon="5.69681450006765" lat="60.3248119894541"/>
 <node lon="5.69596822563358" lat="60.3243967954219"/>
 <node lon="5.69526359757605" lat="60.3242871182594"/>
 <node lon="5.69470250349196" lat="60.3242946968156"/>
 <node lon="5.69430305850483" lat="60.3244192753419"/>
 <node lon="5.69306177038749" lat="60.3253672800549"/>
 <node lon="5.69253260688872" lat="60.325760681757"/>
 <node lon="5.69088045670412" lat="60.327147311"/>
 <node lon="5.69033593186693" lat="60.3280738109471"/>
 <node lon="5.69026519491376" lat="60.3294542357381"/>
 <node lon="5.69027878252719" lat="60.3295554519306"/>
 <node lon="5.68977065367053" lat="60.3301735377793"/>
 <node lon="5.6894749297358" lat="60.3304787339235"/>
 <node lon="5.68886166756668" lat="60.3306363834242"/>
 <node lon="5.68828325616" lat="60.3306739961473"/>
 <node lon="5.68808933373257" lat="60.3306254923988"/>
 <node lon="5.68790486807423" lat="60.3305574061054"/>
 <node lon="5.6878248045111" lat="60.330478794997"/>
 <node lon="5.6878790467577" lat="60.3302348321397"/>
 <node lon="5.68773983208943" lat="60.3302529321173"/>
 <node lon="5.68762011918333" lat="60.3302006296305"/>
 <node lon="5.6873455498382" lat="60.3302094382485"/>
 <node lon="5.68725009828772" lat="60.3301697881462"/>
 <node lon="5.68710743318392" lat="60.3301821291018"/>
 <node lon="5.68696246212518" lat="60.330288778268"/>
 <node lon="5.68687121342971" lat="60.3303068308071"/>
 <node lon="5.68672752686654" lat="60.3302840227909"/>
 <node lon="5.68667556907009" lat="60.3300930365175"/>
 <node lon="5.68631188016073" lat="60.3298067081538"/>
 <node lon="5.68603825319444" lat="60.329807805798"/>
 <node lon="5.68587884793988" lat="60.3299005967004"/>
 <node lon="5.68546354941792" lat="60.3301370374421"/>
 <node lon="5.68483413449837" lat="60.3304377208322"/>
 <node lon="5.68468731935124" lat="60.3303915461758"/>
 <node lon="5.68453429119559" lat="60.3302509126727"/>
 <node lon="5.68440087178693" lat="60.3301930278054"/>
 <node lon="5.68424494092226" lat="60.3301005546036"/>
 <node lon="5.68428253327577" lat="60.3299659787831"/>
 <node lon="5.68428598851937" lat="60.3297414799025"/>
 <node lon="5.6843391853998" lat="60.3296591752623"/>
 <node lon="5.68441748342112" lat="60.329629089654"/>
 <node lon="5.68442797482879" lat="60.3294314858936"/>
 <node lon="5.68433995116184" lat="60.3293818715303"/>
 <node lon="5.6843185989262" lat="60.3292449381444"/>
 <node lon="5.68423459514388" lat="60.3291337717934"/>
 <node lon="5.68423922196375" lat="60.3290643977021"/>
 <node lon="5.6841967614846" lat="60.3290097765243"/>
 <node lon="5.68422475991514" lat="60.3288838343336"/>
 <node lon="5.68413989772663" lat="60.3287458477748"/>
 <node lon="5.68414096251542" lat="60.3286945738506"/>
 <node lon="5.68411516993128" lat="60.3285978273347"/>
 <node lon="5.684027641754" lat="60.3285204937865"/>
 <node lon="5.68388481418891" lat="60.3285080489009"/>
 <node lon="5.6838614008058" lat="60.3284182507115"/>
 <node lon="5.68379128185459" lat="60.3282993865125"/>
 <node lon="5.68378423693565" lat="60.3281380607423"/>
 <node lon="5.68366332213801" lat="60.3279377688715"/>
 <node lon="5.68362453205469" lat="60.3278710215404"/>
 <node lon="5.68358018456556" lat="60.3277747714594"/>
 <node lon="5.68352828664487" lat="60.3276863952183"/>
 <node lon="5.68350181741572" lat="60.3276059636946"/>
 <node lon="5.68334681582827" lat="60.3273422397004"/>
 <node lon="5.6832501158711" lat="60.3272435547093"/>
 <node lon="5.68316306564234" lat="60.3271874085545"/>
 <node lon="5.68208623120332" lat="60.3269219842359"/>
 <node lon="5.68177202615938" lat="60.3268911836545"/>
 <node lon="5.68166375982897" lat="60.326865087389"/>
 <node lon="5.68034147493822" lat="60.326642413688"/>
 <node lon="5.67828411938187" lat="60.3261294364886"/>
 <node lon="5.67807742194796" lat="60.3260709720654"/>
 <node lon="5.67798881555824" lat="60.3260456301059"/>
 <node lon="5.67749484913354" lat="60.3258830424346"/>
 <node lon="5.67733551524401" lat="60.3257968275927"/>
 <node lon="5.67704311747347" lat="60.3255730072004"/>
 <node lon="5.67698799494284" lat="60.325534573731"/>
 <node lon="5.67688902478818" lat="60.325441327397"/>
 <node lon="5.67679907164159" lat="60.325363635509"/>
 <node lon="5.6766875595109" lat="60.3253051211488"/>
 <node lon="5.67657955990977" lat="60.325222355544"/>
 <node lon="5.67646303383265" lat="60.3251343760519"/>
 <node lon="5.67635960611195" lat="60.325056634653"/>
 <node lon="5.67624213662486" lat="60.3249681361525"/>
 <node lon="5.67613052052825" lat="60.3248992173417"/>
 <node lon="5.67606037268728" lat="60.3248116252886"/>
 <node lon="5.67601187046056" lat="60.3247280053654"/>
 <node lon="5.67596591849677" lat="60.3246386895349"/>
 <node lon="5.67591169612712" lat="60.3245464380853"/>
 <node lon="5.67585671444302" lat="60.3244695016485"/>
 <node lon="5.67578153705414" lat="60.3243740499904"/>
 <node lon="5.67569669864123" lat="60.3243083811198"/>
 <node lon="5.67560001353078" lat="60.3242312967405"/>
 <node lon="5.67550990683154" lat="60.3241364159557"/>
 <node lon="5.67542607617247" lat="60.3240336618838"/>
 <node lon="5.67535084925764" lat="60.323936488689"/>
 <node lon="5.67527301978675" lat="60.3238401257527"/>
 <node lon="5.67525714331531" lat="60.3237692101776"/>
 <node lon="5.67526154551933" lat="60.3236677260935"/>
 <node lon="5.6752499485362" lat="60.3235749641704"/>
 <node lon="5.6752371976198" lat="60.3234678366836"/>
 <node lon="5.67522003613043" lat="60.3234400435631"/>
 <node lon="5.67519002919866" lat="60.3233916334218"/>
 <node lon="5.67510128293485" lat="60.3233085106477"/>
 <node lon="5.67506745799312" lat="60.3232866804956"/>
 <node lon="5.67496297125712" lat="60.3232196208049"/>
 <node lon="5.67486917378641" lat="60.3231394854099"/>
 <node lon="5.67482763671091" lat="60.3231045432796"/>
 <node lon="5.6747530897279" lat="60.3230417714359"/>
 <node lon="5.6747424131209" lat="60.3230186860768"/>
 <node lon="5.67471183905553" lat="60.3229519739173"/>
 <node lon="5.67458684945931" lat="60.3228554377255"/>
 <node lon="5.67447092014784" lat="60.32275719194"/>
 <node lon="5.67433621060911" lat="60.3226672000595"/>
 <node lon="5.67420841002249" lat="60.3226266962166"/>
 <node lon="5.67415309880436" lat="60.3226092217168"/>
 <node lon="5.67403235303318" lat="60.3225251897886"/>
 <node lon="5.67401177375052" lat="60.3224991435001"/>
 <node lon="5.67398690505314" lat="60.322467731019"/>
 <node lon="5.67397061527932" lat="60.3224470509157"/>
 <node lon="5.67392390147937" lat="60.3223445714012"/>
 <node lon="5.67387942018447" lat="60.3222767844376"/>
 <node lon="5.67384658281037" lat="60.3222268174947"/>
 <node lon="5.67384364724702" lat="60.3222249824812"/>
 <node lon="5.67376441114755" lat="60.3221709185578"/>
 <node lon="5.67368878309871" lat="60.3220688337647"/>
 <node lon="5.67359057068786" lat="60.3219704846057"/>
 <node lon="5.67352316257907" lat="60.3218721455253"/>
 <node lon="5.67339481037102" lat="60.3217714824891"/>
 <node lon="5.67324840797313" lat="60.3217253216688"/>
 <node lon="5.6730462819726" lat="60.3217207811622"/>
 <node lon="5.67290590360981" lat="60.3216758598882"/>
 <node lon="5.67289069175032" lat="60.3216710767338"/>
 <node lon="5.67277977592387" lat="60.321580145014"/>
 <node lon="5.67271494855951" lat="60.3214817168002"/>
 <node lon="5.67262769060995" lat="60.3213883910117"/>
 <node lon="5.67255127864942" lat="60.3212928493977"/>
 <node lon="5.67246420755174" lat="60.321223584381"/>
 <node lon="5.67226425560754" lat="60.3213103245341"/>
 <node lon="5.67069402361928" lat="60.3216771516089"/>
 <node lon="5.67043064961478" lat="60.3213546558974"/>
 <node lon="5.67002009813541" lat="60.3208867652535"/>
 <node lon="5.66960890031209" lat="60.3204458582175"/>
 <node lon="5.66817785080199" lat="60.317515749405"/>
 <node lon="5.66626792010156" lat="60.3168369677658"/>
 <node lon="5.6659169357251" lat="60.3159384270802"/>
 <node lon="5.66558018785832" lat="60.315345017884"/>
 <node lon="5.66192390364395" lat="60.315451026609"/>
 <node lon="5.65249858981295" lat="60.3150721502823"/>
 <node lon="5.6397121599005" lat="60.3162679241457"/>
 <node lon="5.62726259909829" lat="60.285927485737"/>
 <node lon="5.61498043280735" lat="60.2881221799441"/>
 <node lon="5.61404422371026" lat="60.2882605997584"/>
 <node lon="5.61331132027182" lat="60.2883798718299"/>
 <node lon="5.61302393920579" lat="60.2884277384671"/>
 <node lon="5.61292407793186" lat="60.2884474724793"/>
 <node lon="5.61286634316849" lat="60.2884594503118"/>
 <node lon="5.61276959656523" lat="60.2884759705776"/>
 <node lon="5.61228116970294" lat="60.2885596828898"/>
 <node lon="5.61109288531257" lat="60.2887635633079"/>
 <node lon="5.60873912001442" lat="60.2891206616977"/>
 <node lon="5.60806127855964" lat="60.2892364191997"/>
 <node lon="5.60367402608883" lat="60.2899444852867"/>
 <node lon="5.59788357116811" lat="60.2911624439579"/>
 <node lon="5.59541846818618" lat="60.2902734132422"/>
 <node lon="5.59405855553122" lat="60.2897805411368"/>
 <node lon="5.59158136833509" lat="60.2894433630607"/>
 <node lon="5.58919491434234" lat="60.2891194012232"/>
 <node lon="5.58563132504386" lat="60.2881352919684"/>
 <node lon="5.58285753021643" lat="60.2872022276935"/>
 <node lon="5.58213598403803" lat="60.2869630989576"/>
 <node lon="5.58191346205257" lat="60.286900257121"/>
 <node lon="5.58175449045629" lat="60.2868487416567"/>
 <node lon="5.5794281088875" lat="60.287262978056"/>
 <node lon="5.57662547988482" lat="60.2882044939586"/>
 <node lon="5.57414451342523" lat="60.2879074797504"/>
 <node lon="5.57403802147129" lat="60.2879499478506"/>
 <node lon="5.57050220467302" lat="60.2891423902477"/>
 <node lon="5.5717475829492" lat="60.2905938004945"/>
 <node lon="5.57182853433243" lat="60.2909778141248"/>
 <node lon="5.5723386922409" lat="60.2934642987785"/>
 <node lon="5.57328758463341" lat="60.2951720412555"/>
 <node lon="5.57353473852411" lat="60.2956023080889"/>
 <node lon="5.57335579615107" lat="60.297581854364"/>
 <node lon="5.57338716997418" lat="60.2977309383839"/>
 <node lon="5.5737707891924" lat="60.2991568862059"/>
 <node lon="5.57401008260348" lat="60.2999936487535"/>
 <node lon="5.57461280997934" lat="60.3005471903297"/>
 <node lon="5.57596121682337" lat="60.3017920697062"/>
 <node lon="5.58091764143149" lat="60.3049592897629"/>
 <node lon="5.58298756187589" lat="60.3062717610122"/>
 <node lon="5.58404964076671" lat="60.3068664927325"/>
 <node lon="5.58480486246292" lat="60.3075190298355"/>
 <node lon="5.58503201252077" lat="60.3092762326123"/>
 <node lon="5.58521518445297" lat="60.3101605760219"/>
 <node lon="5.58482761686712" lat="60.3110635347185"/>
 <node lon="5.5841697489116" lat="60.3120656210023"/>
 <node lon="5.58337427915369" lat="60.3132771317821"/>
 <node lon="5.58170054233922" lat="60.3169538298724"/>
 <node lon="5.58245811779629" lat="60.320760557783"/>
 <node lon="5.58332032327441" lat="60.325063547498"/>
 <node lon="5.5854840415575" lat="60.3280848074822"/>
 <node lon="5.57640332244716" lat="60.3295204668834"/>
 <node lon="5.58825437607513" lat="60.3392350189898"/>
 <node lon="5.59122116348111" lat="60.3416383196825"/>
 <node lon="5.59130567457504" lat="60.3419257269969"/>
 <node lon="5.59140141694196" lat="60.3494579172018"/>
 <node lon="5.59110054493252" lat="60.3512107811874"/>
 <node lon="5.59107952236724" lat="60.3513339654908"/>
 <node lon="5.59106515867144" lat="60.3514493066465"/>
 <node lon="5.5910304066703" lat="60.3515556883466"/>
 <node lon="5.59097537858183" lat="60.3516709306597"/>
 <node lon="5.59092711618659" lat="60.3517873791008"/>
 <node lon="5.59090408000842" lat="60.3518747956104"/>
 <node lon="5.59088043526701" lat="60.35201578575"/>
 <node lon="5.5908842640798" lat="60.3521614488917"/>
 <node lon="5.5908902977904" lat="60.3522813198059"/>
 <node lon="5.59088028219614" lat="60.3524268992001"/>
 <node lon="5.59084344126222" lat="60.3525410885581"/>
 <node lon="5.59081797222138" lat="60.352641893996"/>
 <node lon="5.59081785175366" lat="60.3526498420638"/>
 <node lon="5.59082227309749" lat="60.3526710438096"/>
 <node lon="5.59082451027302" lat="60.3526978763603"/>
 <node lon="5.59082430819335" lat="60.3527079886037"/>
 <node lon="5.59081975087083" lat="60.3527236671438"/>
 <node lon="5.59081039621571" lat="60.352748316266"/>
 <node lon="5.59080123539095" lat="60.3527886212993"/>
 <node lon="5.59078959157675" lat="60.3528311903996"/>
 <node lon="5.59077781752995" lat="60.3528748352073"/>
 <node lon="5.59076204330029" lat="60.3529140354011"/>
 <node lon="5.5907319968575" lat="60.3529835013066"/>
 <node lon="5.59069514011465" lat="60.3530707454009"/>
 <node lon="5.59066095277203" lat="60.3531412720658"/>
 <node lon="5.59061743130985" lat="60.3532162864017"/>
 <node lon="5.59056487439179" lat="60.3532991551338"/>
 <node lon="5.59050753284117" lat="60.3533852990952"/>
 <node lon="5.59044378208346" lat="60.3534702623497"/>
 <node lon="5.59038665466854" lat="60.3535519007374"/>
 <node lon="5.59034774849753" lat="60.3536078952214"/>
 <node lon="5.59029523648455" lat="60.3536818158663"/>
 <node lon="5.59024714150102" lat="60.353745563368"/>
 <node lon="5.59020389255657" lat="60.3538014287612"/>
 <node lon="5.59013082868162" lat="60.3538920565231"/>
 <node lon="5.59006490174163" lat="60.3539782206557"/>
 <node lon="5.59001675726749" lat="60.3540408795883"/>
 <node lon="5.58996869641908" lat="60.3541114107416"/>
 <node lon="5.58992062501173" lat="60.3541863715582"/>
 <node lon="5.58986608250472" lat="60.3542647584894"/>
 <node lon="5.5898064564839" lat="60.3543430538819"/>
 <node lon="5.5897219093848" lat="60.3544493179148"/>
 <node lon="5.58966033878487" lat="60.3545286499229"/>
 <node lon="5.58958969490156" lat="60.354631656532"/>
 <node lon="5.58950522897687" lat="60.3547244541847"/>
 <node lon="5.58942998576205" lat="60.3547949441144"/>
 <node lon="5.58935495910369" lat="60.3548709649034"/>
 <node lon="5.58927965623972" lat="60.3549447959504"/>
 <node lon="5.58921806743538" lat="60.354998448158"/>
 <node lon="5.5891133873307" lat="60.3550936005361"/>
 <node lon="5.58902930026233" lat="60.3551762983599"/>
 <node lon="5.58896093215591" lat="60.3552444758738"/>
 <node lon="5.58887421721088" lat="60.3553362086201"/>
 <node lon="5.58879901836681" lat="60.355419088628"/>
 <node lon="5.58874881589781" lat="60.3554750000227"/>
 <node lon="5.58867349963289" lat="60.3555532603457"/>
 <node lon="5.58858928907839" lat="60.3556439058939"/>
 <node lon="5.58851600242564" lat="60.3557277360458"/>
 <node lon="5.58844993540394" lat="60.3558262769349"/>
 <node lon="5.58838601631217" lat="60.3559023668556"/>
 <node lon="5.5883176937075" lat="60.3559716324403"/>
 <node lon="5.58823090517587" lat="60.3560711355782"/>
 <node lon="5.58818541288955" lat="60.3561114696418"/>
 <node lon="5.5881444100324" lat="60.3561438961713"/>
 <node lon="5.58807184842759" lat="60.3561693685046"/>
 <node lon="5.58796974017667" lat="60.3562010502692"/>
 <node lon="5.58339144805768" lat="60.3583806601305"/>
 <node lon="5.58503064640422" lat="60.3646580351298"/>
 <node lon="5.58629452191291" lat="60.3694964406924"/>
 <node lon="5.58759852948483" lat="60.3745437467383"/>
 <node lon="5.57920200438508" lat="60.3775480982456"/>
 <node lon="5.58761352305247" lat="60.3849225074357"/>
 <node lon="5.58764913396506" lat="60.3849764954917"/>
 <node lon="5.59070670637451" lat="60.3876503994552"/>
 <node lon="5.60695581235824" lat="60.397231419865"/>
 <node lon="5.61261572378745" lat="60.3983121195322"/>
 <node lon="5.61449849966874" lat="60.398683171128"/>
 <node lon="5.6174520450616" lat="60.3992327522138"/>
 <node lon="5.62228949351829" lat="60.400087362481"/>
 <node lon="5.62483613195583" lat="60.4004277531784"/>
 <node lon="5.62803130907326" lat="60.4008496721655"/>
 <node lon="5.63201251394014" lat="60.4013706931254"/>
 <node lon="5.63371728373667" lat="60.4015916625737"/>
 <node lon="5.63458048113724" lat="60.4017074263089"/>
 <node lon="5.63615104391081" lat="60.4019129639819"/>
 <node lon="5.63655282696621" lat="60.4019649712094"/>
 <node lon="5.63931937498663" lat="60.4023274463308"/>
 <node lon="5.64064931104215" lat="60.4025032970835"/>
 <node lon="5.64264143736425" lat="60.4027584415895"/>
 <node lon="5.64342230547882" lat="60.4029870175226"/>
 <node lon="5.64368216524867" lat="60.4031120297662"/>
 <node lon="5.64524648158532" lat="60.4038639929457"/>
 <node lon="5.64534489608818" lat="60.4039116515219"/>
 <node lon="5.64545785799083" lat="60.4039734503618"/>
 <node lon="5.64562109727457" lat="60.4040661156658"/>
 <node lon="5.64574857616233" lat="60.4041497372527"/>
 <node lon="5.64625019123732" lat="60.4045766661211"/>
 <node lon="5.6467061815662" lat="60.4075125899081"/>
 <node lon="5.64943826269654" lat="60.4108985844713"/>
 <node lon="5.65188099644395" lat="60.41319808228"/>
 <node lon="5.6531879297339" lat="60.414446128248"/>
 <node lon="5.65595124577808" lat="60.4186835379813"/>
 <node lon="5.66379389273855" lat="60.4202975443039"/>
 <node lon="5.6649456922349" lat="60.4200336976909"/>
 <node lon="5.6738332307371" lat="60.4224137998757"/>
 <node lon="5.67916259433926" lat="60.4238603417547"/>
 <node lon="5.68010237873376" lat="60.4240977090201"/>
 <node lon="5.68055932796485" lat="60.4242397054571"/>
 <node lon="5.68169695440664" lat="60.4245430937342"/>
 <node lon="5.68202755431958" lat="60.4246312385798"/>
 <node lon="5.68679142540914" lat="60.4259014824334"/>
 <node lon="5.68665640727503" lat="60.4287577205372"/>
 <node lon="5.68644569343405" lat="60.4357554342701"/>
</polygon>
