<polyline>
<node lon="10.2644759" lat="63.2809593" />
<node lon="10.2648437" lat="63.2809188" />
<node lon="10.2656092" lat="63.2807989" />
<node lon="10.2660886" lat="63.2807335" />
<node lon="10.266438" lat="63.2806931" />
<node lon="10.2669047" lat="63.2806487" />
<node lon="10.2673305" lat="63.2806144" />
<node lon="10.26783" lat="63.2805857" />
<node lon="10.2682847" lat="63.280571" />
<node lon="10.2687373" lat="63.2805637" />
<node lon="10.2691443" lat="63.2805661" />
<node lon="10.2694997" lat="63.2805734" />
<node lon="10.2699691" lat="63.2805887" />
<node lon="10.2704117" lat="63.280613" />
<node lon="10.2707872" lat="63.2806403" />
<node lon="10.2712525" lat="63.2806801" />
<node lon="10.2716401" lat="63.2807217" />
<node lon="10.2719995" lat="63.2807699" />
<node lon="10.2724555" lat="63.2808333" />
</polyline>